Workbook

Sheet Ranking
A1: EOS-DENO · Ranking dos 14 produtos (probabilidade de aderência × receita · BR)
A2: Notas de aderência e receita são julgamento [H], escala 1–5. Score = Prob × Receita. Top 5 destacados. Eixos: aderência = chance de PMF no BR hoje; receita = potencial de receita BR.
A4: # | B4: Produto | C4: Fundação | D4: Prob. aderência BR [H] | E4: Potencial receita BR [H] | F4: Score | G4: Tier | H4: Seleção
A5: 1 | B5: P2 · EOS GD | C5: SW | D5: 5 | E5: 4 | F5: =D5*E5 -> 20 | G5: T1 | H5: ✓ TOP 5
A6: 2 | B6: P1 · EOS Integrador | C6: SW | D6: 5 | E6: 3 | F6: =D6*E6 -> 15 | G6: T1 | H6: ✓ TOP 5
A7: 3 | B7: P4 · EOS OS (licença) | C7: SW | D7: 3 | E7: 5 | F7: =D7*E7 -> 15 | G7: T1.5 | H7: ✓ TOP 5
A8: 4 | B8: P5 · EOS Meter MaaS | C8: HW | D8: 3 | E8: 4 | F8: =D8*E8 -> 12 | G8: T1.5 | H8: ✓ TOP 5
A9: 5 | B9: P7 · EOS Canal | C9: SW⊕HW | D9: 4 | E9: 3 | F9: =D9*E9 -> 12 | G9: T1 | H9: ✓ TOP 5
A10: 6 | B10: P6 · EOS Hub | C10: HW | D10: 4 | E10: 3 | F10: =D10*E10 -> 12 | G10: T1 | H10: ≈ 6º (empate)
A11: 7 | B11: P8 · EOS ACL | C11: SW | D11: 2 | E11: 5 | F11: =D11*E11 -> 10 | G11: T2
A12: 8 | B12: P9 · EOS Comercializadora | C12: SW→Reg | D12: 2 | E12: 4 | F12: =D12*E12 -> 8 | G12: T2
A13: 9 | B13: P3 · EOS Consumo | C13: SW⊕HW | D13: 4 | E13: 2 | F13: =D13*E13 -> 8 | G13: T1
A14: 10 | B14: P10 · EOS Grid | C14: SW⊕HW | D14: 2 | E14: 3 | F14: =D14*E14 -> 6 | G14: T2/T3
A15: 11 | B15: P11 · EOS Flex / VPP | C15: SW | D15: 1 | E15: 4 | F15: =D15*E15 -> 4 | G15: T3
A16: 12 | B16: P12 · EOS Dados | C16: SW | D16: 2 | E16: 2 | F16: =D16*E16 -> 4 | G16: T3
A17: 13 | B17: P14 · EOS P2P | C17: SW | D17: 1 | E17: 1 | F17: =D17*E17 -> 1 | G17: T3
A18: 14 | B18: P13 · EOS Agentes (habilitador) | C18: SW | F18: n/a | G18: T3 | H18: habilitador
B20: Empate em 12 (P5, P6, P7): escolhidos P5 (hardware-licenciamento, modelo Intellihub) e P7 (alavanca empresa-âncora). P6 é o 6º imediato.

Sheet Premissas
A1: EOS-DENO · Premissas de unit economics (top 5 produtos)
A2: Toda linha carrega rótulo. [F] fato c/ fonte · [E] estimativa fundamentada · [H] hipótese · [INPUT] placeholder ilustrativo. Valores em azul são entradas (editáveis p/ cenário). Fundo amarelo = entrada que precisa de validação em deep-dive.
A4: Produto | B4: Parâmetro | C4: Valor | D4: Unid. | E4: Rótulo | F4: Fonte / Racional
A5: P1 Integrador | B5: ARPU | C5: 600 | D5: R$/integrador/mês | E5: INPUT | F5: Faixa R$200–1.500/mês (REV-01 R-01); ponto conservador-médio
A6: P1 Integrador | B6: Margem bruta | C6: 0.8 | D6: % | E6: E | F6: SaaS típico
A7: P1 Integrador | B7: Churn mensal | C7: 0.02 | D7: % | E7: INPUT | F7: B2B SaaS de nicho
A8: P1 Integrador | B8: CAC | C8: 3000 | D8: R$/integrador | E8: INPUT | F8: Venda + onboarding B2B
A9: P2 GD | B9: ARPU | C9: 4 | D9: R$/UC/mês | E9: INPUT | F9: Faixa R$2–6/UC/mês (REV-01 R-06)
A10: P2 GD | B10: Margem bruta | C10: 0.85 | D10: % | E10: E | F10: SaaS
A11: P2 GD | B11: Churn mensal | C11: 0.015 | D11: % | E11: INPUT | F11: Churn da gestora (cliente) baixo; UCs flutuam
A12: P2 GD | B12: CAC | C12: 30 | D12: R$/UC | E12: INPUT | F12: Aquisição em lote via gestora
A13: P4 OS-licença | B13: Preço anual | C13: 18 | D13: R$/UC/ano | E13: INPUT | F13: Faixa R$8–35; Kraken US$7,1≈R$35 [F] c/ deflator ~50% → [E]
A14: P4 OS-licença | B14: Margem bruta | C14: 0.85 | D14: % | E14: E | F14: Licenciamento de software
A15: P4 OS-licença | B15: Churn mensal | C15: 0.007 | D15: % | E15: INPUT | F15: ≈8%/ano; licença enterprise sticky
A16: P4 OS-licença | B16: CAC | C16: 10 | D16: R$/UC | E16: INPUT | F16: Amortizado sobre deal — ALTAMENTE sensível ao tamanho do deal
... A26: P7 Canal | B26: CAC | C26: 3000 | D26: R$/integrador | E26: INPUT | F26: Compartilhado com P1

Sheet Unit Economics
A1: EOS-DENO · Unit Economics (top 5 produtos) — modelo ilustrativo
A2: Entradas (verde) puxam da aba Premissas; métricas (preto) são fórmulas. Régua da skill: LTV:CAC ≥ 3,0x e payback < 12 meses. Modelo de demonstração — números a validar (ver aba Leitura).
A4: Métrica | B4: P1 EOS Integrador | C4: P2 EOS GD | D4: P4 EOS OS (licença) | E4: P5 EOS Meter MaaS | F4: P7 EOS Canal
A5: Fundação · modelo | B5: SW · SaaS | C5: SW · SaaS | D5: SW · licença | E5: HW · MaaS | F5: ⊕ · take-rate
A6: Unidade de cobrança | B6: por integrador | C6: por UC | D6: por UC | E6: por medidor | F6: por integrador
A7: ARPU mensal | B7: =Premissas!C5 -> 600 | C7: =Premissas!C9 -> 4 | D7: =Premissas!C13/12 -> 1.5 | E7: =Premissas!C17 -> 8 | F7: =Premissas!C21*Premissas!C22*Premissas!C23/12 -> 2916.6667
A8: Margem bruta | B8: =Premissas!C6 -> 0.8 | C8: =Premissas!C10 -> 0.85 | D8: =Premissas!C14 -> 0.85 | E8: =Premissas!C18 -> 0.45 | F8: =Premissas!C24 -> 0.9
A9: Churn mensal | B9: =Premissas!C7 -> 0.02 | C9: =Premissas!C11 -> 0.015 | D9: =Premissas!C15 -> 0.007 | E9: =Premissas!C19 -> 0.01 | F9: =Premissas!C25 -> 0.025
A10: Tempo de vida (meses) | B10: =1/B9 -> 50 | C10: =1/C9 -> 66.666667 | D10: =1/D9 -> 142.85714 | E10: =1/E9 -> 100 | F10: =1/F9 -> 40
A11: LTV | B11: =B7*B8*B10 -> 24000 | C11: =C7*C8*C10 -> 226.66667 | D11: =D7*D8*D10 -> 182.14286 | E11: =E7*E8*E10 -> 360 | F11: =F7*F8*F10 -> 105000
A12: CAC | B12: =Premissas!C8 -> 3000 | C12: =Premissas!C12 -> 30 | D12: =Premissas!C16 -> 10 | E12: =Premissas!C20 -> 250 | F12: =Premissas!C26 -> 3000
A13: LTV : CAC | B13: =B11/B12 -> 8 | C13: =C11/C12 -> 7.5555556 | D13: =D11/D12 -> 18.214286 | E13: =E11/E12 -> 1.44 | F13: =F11/F12 -> 35
A14: Payback (meses) | B14: =B12/(B7*B8) -> 6.25 | C14: =C12/(C7*C8) -> 8.8235294 | D14: =D12/(D7*D8) -> 7.8431373 | E14: =E12/(E7*E8) -> 69.444444 | F14: =F12/(F7*F8) -> 1.1428571
A15: Veredito (≥3x e <12m) | B15: =IF(AND(B13>=3,B14<12),"PASSA","REVISAR") -> PASSA | C15: =IF(AND(C13>=3,C14<12),"PASSA","REVISAR") -> PASSA | D15: =IF(AND(D13>=3,D14<12),"PASSA","REVISAR") -> PASSA | E15: =IF(AND(E13>=3,E14<12),"PASSA","REVISAR") -> REVISAR | F15: =IF(AND(F13>=3,F14<12),"PASSA","REVISAR") -> PASSA

Sheet Leitura
A1: EOS-DENO · Leitura crítica do modelo (o que estes números dizem — e não dizem)
A3: Natureza do modelo
A4: Demonstração. A maioria das entradas é [INPUT]/[E], não [F]. O valor está na ESTRUTURA e na SENSIBILIDADE, não nos outputs precisos. Deep-dive de PMF/receita/risco fica para sessões futuras (combinado).
A6: ★ Achado P5 (Meter MaaS) NÃO é SaaS
A7: Sob estas entradas: LTV:CAC ~1,4x e payback ~69 meses (~5–6 anos). É economia de INFRAESTRUTURA, não de software: o CapEx do medidor (~R$250) é pago contra um fee fino (R$8/mês). A Intellihub financia isso com ~A$3 bilhões em green loans [F] — o modelo monetiza, mas com ROI de infra e capital barato, não com margem de SaaS. É o risco mais agudo do portfólio de hardware.
A9: Banana-com-banana em P5
A10: A aderência da Intellihub é num mercado (Austrália) com rollout de smart meter MANDATADO. O Brasil não tem mandato [F] → adoção voluntária + necessidade de financiamento. A analogia do MODELO não transfere o TIMING nem o custo de capital.
A12: Achado P4 (licença OS)
A13: O LTV:CAC e o payback dependem fortemente do tamanho do deal (CAC por UC amortizado). A R$10/UC de CAC, fecha bem (estilo Kraken a escala). Sub-escala, o CAC por UC explode e não fecha. A nota [INPUT] esconde essa alavanca — modelar por faixa de tamanho de deal no deep-dive.
A15: Produtos que fecham na régua
A16: P1, P2, P4 e P7 passam (LTV:CAC ≥3x e payback <12m) sob estas entradas. P5 não passa — por desenho do modelo, que revela sua natureza de infra. Isso é sinal, não erro.
A18: P7 (Canal) é o mais lucrativo no papel
... A25: 3 conversas reais de pricing por produto (varejista p/ P4; gestora p/ P2; integrador p/ P1/P7; varejista/DSO p/ P5) substituem [INPUT] por [E]/[F]. Sem isso, o modelo é hipótese estruturada, não evidência.
